{
  "best_valid_loss_normalized": 0.028740115455378662,
  "test": null,
  "seconds": 1128.3117141723633,
  "parameters": {
    "long_hidden": 32,
    "period_hidden": 8,
    "short_hidden": 128,
    "fusion": "attention",
    "fusion_heads": 8,
    "dropout": 0.055526259085939195,
    "learning_rate": 0.0017375213140589521,
    "weight_decay": 1.8141186056662205e-05,
    "batch_size": 16
  },
  "history": [
    {
      "epoch": 1,
      "train_loss": 0.06471783140153448,
      "valid_loss": 0.035870619177743104
    },
    {
      "epoch": 2,
      "train_loss": 0.04547866616777317,
      "valid_loss": 0.03676132430231869
    },
    {
      "epoch": 3,
      "train_loss": 0.040356266287849114,
      "valid_loss": 0.03363388303050081
    },
    {
      "epoch": 4,
      "train_loss": 0.0387827584452203,
      "valid_loss": 0.03300720553418017
    },
    {
      "epoch": 5,
      "train_loss": 0.03657540846453016,
      "valid_loss": 0.030708601201678447
    },
    {
      "epoch": 6,
      "train_loss": 0.03570452964989505,
      "valid_loss": 0.03386656176962036
    },
    {
      "epoch": 7,
      "train_loss": 0.03469415910229712,
      "valid_loss": 0.03126525744077269
    },
    {
      "epoch": 8,
      "train_loss": 0.033923104743441915,
      "valid_loss": 0.029710695682235014
    },
    {
      "epoch": 9,
      "train_loss": 0.03352637784937349,
      "valid_loss": 0.034222811313237934
    },
    {
      "epoch": 10,
      "train_loss": 0.03272771691703566,
      "valid_loss": 0.029661679671221432
    },
    {
      "epoch": 11,
      "train_loss": 0.032330617864578894,
      "valid_loss": 0.030323729658447665
    },
    {
      "epoch": 12,
      "train_loss": 0.032207071204604996,
      "valid_loss": 0.030855642090140856
    },
    {
      "epoch": 13,
      "train_loss": 0.031770210212095716,
      "valid_loss": 0.028785138124381257
    },
    {
      "epoch": 14,
      "train_loss": 0.031720830487084795,
      "valid_loss": 0.029266632651585908
    },
    {
      "epoch": 15,
      "train_loss": 0.0313214542792929,
      "valid_loss": 0.029778643960056434
    },
    {
      "epoch": 16,
      "train_loss": 0.03131943898389604,
      "valid_loss": 0.02899840762063272
    },
    {
      "epoch": 17,
      "train_loss": 0.03131557069633041,
      "valid_loss": 0.029565278485622064
    },
    {
      "epoch": 18,
      "train_loss": 0.03113102373499329,
      "valid_loss": 0.030454276730641952
    },
    {
      "epoch": 19,
      "train_loss": 0.03017304061758853,
      "valid_loss": 0.029575407868478357
    },
    {
      "epoch": 20,
      "train_loss": 0.03015434682602599,
      "valid_loss": 0.028740115455378662
    }
  ]
}